nlp_tir-0.1.0a1.dist-info/METADATA
nlp_tir-0.1.0a1.dist-info/WHEEL
nlp_tir/.ipynb_checkpoints/datasets-checkpoint.py
nlp_tir/.ipynb_checkpoints/setup-checkpoint.py
nlp_tir/__init__.py
nlp_tir/datasets.py
nlp_tir/setup.py
nlp_tir-0.1.0a1.dist-info/RECORD
